apsniper0673_stockutil-0.1.11.dist-info/licenses/LICENSE
mystockutil/__init__.py
mystockutil/api.py
mystockutil/ds.py
mystockutil/etc.py
mystockutil/trader_window_manager.py
mystockutil/type_convert.py
mystockutil/df/format.py
mystockutil/df/type.py
mystockutil/df/voperation.py
mystockutil/logging/__init__.py
mystockutil/logging/logging_setup.py
mystockutil/messenger/__init__.py
mystockutil/messenger/discord/__init__.py
mystockutil/messenger/discord/sender.py
mystockutil/naming/__init__.py
mystockutil/naming/name.py
mystockutil/server/__init__.py
mystockutil/server/get_available_server.py
mystockutil/spreadsheet/__init__.py
mystockutil/spreadsheet/spreadsheet_manager.py
apsniper0673_stockutil-0.1.11.dist-info/METADATA
apsniper0673_stockutil-0.1.11.dist-info/WHEEL
apsniper0673_stockutil-0.1.11.dist-info/top_level.txt
apsniper0673_stockutil-0.1.11.dist-info/RECORD
