Metadata-Version: 2.4
Name: apsniper0673_stockutil
Version: 0.1.11
Summary: My stock utility package
Author: sniper0673
Requires-Python: >=3.8
License-File: LICENSE
Dynamic: license-file
